[{"type":"constructor","payable":false,"inputs":[{"type":"address","name":"_userContract"},{"type":"address","name":"_companyContract"}]},{"type":"error","name":"Candidate_Job__AlreadyApplied","inputs":[{"type":"address","name":"candidate_address"},{"type":"uint256","name":"id"}]},{"type":"error","name":"Candidate_Job__NotApplied","inputs":[{"type":"address","name":"candidate_address"},{"type":"uint256","name":"id"}]},{"type":"error","name":"Candidate__NotExisted","inputs":[{"type":"address","name":"user_address"}]},{"type":"error","name":"Job__AlreadyExisted","inputs":[{"type":"uint256","name":"id"}]},{"type":"error","name":"Job__NotExisted","inputs":[{"type":"uint256","name":"id"}]},{"type":"error","name":"Recruiter_Company__NotIn","inputs":[{"type":"address","name":"recruiter_address"},{"type":"uint256","name":"company_id"}]},{"type":"error","name":"Recruiter_Job__NotForSelf","inputs":[{"type":"address","name":"recruiter_address"},{"type":"address","name":"origin_address"}]},{"type":"error","name":"Recruiter_Job__NotOwned","inputs":[{"type":"address","name":"recruiter_address"},{"type":"uint256","name":"job_id"}]},{"type":"error","name":"Recruiter__NotExisted","inputs":[{"type":"address","name":"user_address"}]},{"type":"error","name":"User__NoRole","inputs":[{"type":"address","name":"account"}]},{"type":"error","name":"User__NotPermit","inputs":[{"type":"address","name":"account"}]},{"type":"event","anonymous":false,"name":"AddJob","inputs":[{"type":"tuple","name":"job","indexed":false,"components":[{"type":"uint256","name":"id"},{"type":"string","name":"title"},{"type":"string","name":"location"},{"type":"string","name":"jobType"},{"type":"uint256","name":"experience"},{"type":"string","name":"requirements"},{"type":"string","name":"benefits"},{"type":"uint256","name":"createAt"},{"type":"uint256","name":"updateAt"},{"type":"uint256","name":"companyId"},{"type":"uint256","name":"salary"},{"type":"string","name":"field"},{"type":"address","name":"owner"}]}]},{"type":"event","anonymous":false,"name":"ApplyJob","inputs":[{"type":"address","name":"candidate_address","indexed":true},{"type":"address","name":"recruiter_address","indexed":true},{"type":"uint256","name":"job_id","indexed":false},{"type":"bool","name":"isApplied","indexed":false}]},{"type":"event","anonymous":false,"name":"DeleteJob","inputs":[{"type":"tuple","name":"job","indexed":false,"components":[{"type":"uint256","name":"id"},{"type":"string","name":"title"},{"type":"string","name":"location"},{"type":"string","name":"jobType"},{"type":"uint256","name":"experience"},{"type":"string","name":"requirements"},{"type":"string","name":"benefits"},{"type":"uint256","name":"createAt"},{"type":"uint256","name":"updateAt"},{"type":"uint256","name":"companyId"},{"type":"uint256","name":"salary"},{"type":"string","name":"field"},{"type":"address","name":"owner"}]}]},{"type":"event","anonymous":false,"name":"DisapplyJob","inputs":[{"type":"address","name":"candidate_address","indexed":true},{"type":"address","name":"recruiter_address","indexed":true},{"type":"uint256","name":"job_id","indexed":false},{"type":"bool","name":"isApplied","indexed":false}]},{"type":"event","anonymous":false,"name":"UpdateJob","inputs":[{"type":"tuple","name":"job","indexed":false,"components":[{"type":"uint256","name":"id"},{"type":"string","name":"title"},{"type":"string","name":"location"},{"type":"string","name":"jobType"},{"type":"uint256","name":"experience"},{"type":"string","name":"requirements"},{"type":"string","name":"benefits"},{"type":"uint256","name":"createAt"},{"type":"uint256","name":"updateAt"},{"type":"uint256","name":"companyId"},{"type":"uint256","name":"salary"},{"type":"string","name":"field"},{"type":"address","name":"owner"}]}]},{"type":"function","name":"ADMIN_COMPANY_ROLE","constant":true,"stateMutability":"view","payable":false,"inputs":[],"outputs":[{"type":"bytes32"}]},{"type":"function","name":"CANDIDATE_ROLE","constant":true,"stateMutability":"view","payable":false,"inputs":[],"outputs":[{"type":"bytes32"}]},{"type":"function","name":"RECRUITER_ROLE","constant":true,"stateMutability":"view","payable":false,"inputs":[],"outputs":[{"type":"bytes32"}]},{"type":"function","name":"addJob","constant":false,"payable":false,"inputs":[{"type":"tuple","name":"_job","components":[{"type":"uint256","name":"id"},{"type":"string","name":"title"},{"type":"string","name":"location"},{"type":"string","name":"jobType"},{"type":"uint256","name":"experience"},{"type":"string","name":"requirements"},{"type":"string","name":"benefits"},{"type":"uint256","name":"createAt"},{"type":"uint256","name":"updateAt"},{"type":"uint256","name":"companyId"},{"type":"uint256","name":"salary"},{"type":"string","name":"field"},{"type":"address","name":"owner"}]}],"outputs":[]},{"type":"function","name":"connectJobCandidate","constant":false,"payable":false,"inputs":[{"type":"address","name":"_candidateAddress"},{"type":"uint256","name":"_jobId"}],"outputs":[]},{"type":"function","name":"deleteJob","constant":false,"payable":false,"inputs":[{"type":"uint256","name":"_id"}],"outputs":[]},{"type":"function","name":"disconnectJobCandidate","constant":false,"payable":false,"inputs":[{"type":"address","name":"_candidateAddress"},{"type":"uint256","name":"_jobId"}],"outputs":[]},{"type":"function","name":"getAllAppliedCandidatesOf","constant":true,"stateMutability":"view","payable":false,"inputs":[{"type":"uint256","name":"_jobId"}],"outputs":[{"type":"address[]"}]},{"type":"function","name":"getAllAppliedJobsOf","constant":true,"stateMutability":"view","payable":false,"inputs":[{"type":"address","name":"_candidate"}],"outputs":[{"type":"tuple[]","components":[{"type":"uint256","name":"id"},{"type":"string","name":"title"},{"type":"string","name":"location"},{"type":"string","name":"jobType"},{"type":"uint256","name":"experience"},{"type":"string","name":"requirements"},{"type":"string","name":"benefits"},{"type":"uint256","name":"createAt"},{"type":"uint256","name":"updateAt"},{"type":"uint256","name":"companyId"},{"type":"uint256","name":"salary"},{"type":"string","name":"field"},{"type":"address","name":"owner"}]}]},{"type":"function","name":"getAllJobs","constant":true,"stateMutability":"view","payable":false,"inputs":[],"outputs":[{"type":"tuple[]","components":[{"type":"uint256","name":"id"},{"type":"string","name":"title"},{"type":"string","name":"location"},{"type":"string","name":"jobType"},{"type":"uint256","name":"experience"},{"type":"string","name":"requirements"},{"type":"string","name":"benefits"},{"type":"uint256","name":"createAt"},{"type":"uint256","name":"updateAt"},{"type":"uint256","name":"companyId"},{"type":"uint256","name":"salary"},{"type":"string","name":"field"},{"type":"address","name":"owner"}]}]},{"type":"function","name":"getAllJobsOf","constant":true,"stateMutability":"view","payable":false,"inputs":[{"type":"address","name":"_recruiterAddress"}],"outputs":[{"type":"tuple[]","components":[{"type":"uint256","name":"id"},{"type":"string","name":"title"},{"type":"string","name":"location"},{"type":"string","name":"jobType"},{"type":"uint256","name":"experience"},{"type":"string","name":"requirements"},{"type":"string","name":"benefits"},{"type":"uint256","name":"createAt"},{"type":"uint256","name":"updateAt"},{"type":"uint256","name":"companyId"},{"type":"uint256","name":"salary"},{"type":"string","name":"field"},{"type":"address","name":"owner"}]}]},{"type":"function","name":"getJob","constant":true,"stateMutability":"view","payable":false,"inputs":[{"type":"uint256","name":"_id"}],"outputs":[{"type":"tuple","components":[{"type":"uint256","name":"id"},{"type":"string","name":"title"},{"type":"string","name":"location"},{"type":"string","name":"jobType"},{"type":"uint256","name":"experience"},{"type":"string","name":"requirements"},{"type":"string","name":"benefits"},{"type":"uint256","name":"createAt"},{"type":"uint256","name":"updateAt"},{"type":"uint256","name":"companyId"},{"type":"uint256","name":"salary"},{"type":"string","name":"field"},{"type":"address","name":"owner"}]}]},{"type":"function","name":"getLatestJobId","constant":true,"stateMutability":"view","payable":false,"inputs":[],"outputs":[{"type":"uint256"}]},{"type":"function","name":"isExistedJob","constant":true,"stateMutability":"view","payable":false,"inputs":[{"type":"uint256","name":"_jobId"}],"outputs":[{"type":"bool"}]},{"type":"function","name":"isOwnerOfJob","constant":true,"stateMutability":"view","payable":false,"inputs":[{"type":"address","name":"_recruiterAddress"},{"type":"uint256","name":"_jobId"}],"outputs":[{"type":"bool"}]},{"type":"function","name":"setCompanyInterface","constant":false,"payable":false,"inputs":[{"type":"address","name":"_contract"}],"outputs":[]},{"type":"function","name":"setUserInterface","constant":false,"payable":false,"inputs":[{"type":"address","name":"_contract"}],"outputs":[]},{"type":"function","name":"updateJob","constant":false,"payable":false,"inputs":[{"type":"tuple","name":"_job","components":[{"type":"uint256","name":"id"},{"type":"string","name":"title"},{"type":"string","name":"location"},{"type":"string","name":"jobType"},{"type":"uint256","name":"experience"},{"type":"string","name":"requirements"},{"type":"string","name":"benefits"},{"type":"uint256","name":"createAt"},{"type":"uint256","name":"updateAt"},{"type":"uint256","name":"companyId"},{"type":"uint256","name":"salary"},{"type":"string","name":"field"},{"type":"address","name":"owner"}]}],"outputs":[]}]